<?xml version = '1.0' encoding = 'UTF-8'?>
<Relation class="oracle.dbtools.crest.model.design.logical.Relation" name="user_add" directorySegmentName="seg_0" id="33C0B60F-372C-713C-9ABF-446E00BC5E9E">
<createdBy>saikirancvn</createdBy>
<createdTime>2021-03-31 21:53:08 UTC</createdTime>
<ownerDesignName>ringer</ownerDesignName>
<engineerTo>
<item key="2FECD5DD-8AA8-8009-54C8-AB35D9CA7AED" value="true"/>
</engineerTo>
<sourcePk>F2717351-30A8-1782-7191-E25DE07BD73E</sourcePk>
<identifying>false</identifying>
<optionalSource>false</optionalSource>
<optionalTarget>false</optionalTarget>
<sourceCardinality>1</sourceCardinality>
<sourceEntity>73FE4CAC-32B9-8BD6-E81A-938B48068209</sourceEntity>
<targetCardinalityString>*</targetCardinalityString>
<targetEntity>D5B7A6C3-D3B6-80B4-E196-87CD36F0F33F</targetEntity>
<transferable>true</transferable>
<deleteRule>NO ACTION</deleteRule>
</Relation>